nonebot_plugin_impart/__init__.py
nonebot_plugin_impart/config.py
nonebot_plugin_impart/data_sheet.py
nonebot_plugin_impart/draw_img.py
nonebot_plugin_impart/handle.py
nonebot_plugin_impart/fonts/SIMYOU.TTF
nonebot_plugin_impart-0.1.2.5.3.dist-info/LICENSE
nonebot_plugin_impart-0.1.2.5.3.dist-info/METADATA
nonebot_plugin_impart-0.1.2.5.3.dist-info/WHEEL
nonebot_plugin_impart-0.1.2.5.3.dist-info/top_level.txt
nonebot_plugin_impart-0.1.2.5.3.dist-info/RECORD
