Metadata-Version: 2.1
Name: nonebot-plugin-impart
Version: 0.1.2.5.3
Summary: NoneBot2 Impart Plugin Plus
Home-page: https://github.com/YuuzukiRin/nonebot_plugin_impart
Author: YuuzukiRin
Author-email: yuuzukirin@outlook.com
Classifier: Programming Language :: Python :: 3
Classifier: Programming Language :: Python :: 3.8
Classifier: Programming Language :: Python :: 3.9
Classifier: Programming Language :: Python :: 3.10
Classifier: License :: OSI Approved :: MIT License
Classifier: Operating System :: OS Independent
Requires-Python: >=3.8
License-File: LICENSE
Requires-Dist: nonebot2 >=2.2.0
Requires-Dist: nonebot-plugin-localstore >=0.7.0
Requires-Dist: nonebot-adapter-onebot >=2.4.4
Requires-Dist: nonebot-plugin-apscheduler >=0.4.0
Requires-Dist: Pillow >=10.2.0
Requires-Dist: httpx >=0.27.0
Requires-Dist: sqlalchemy >=2.0.20
Requires-Dist: aiosqlite >=0.19.0
